<odoo>
    <data>
        <record id="my_view_for_policy_form2" model="ir.ui.view">
            <field name="name">policy Form2</field>
            <field name="model">proposal.bb</field>
            <field name="arch" type="xml">
                <form string="my policy form2">

                    <div class="o_row">
                        <label for="Company"/>
                        <field name="Company"/>
                        <label for="product_pol"/>
                        <field name="product_pol"/>
                        <label for="premium"/>
                        <field name="premium"/>
                        <button name="create_covers" string="Generate Proposal" class="oe_highlight" type="object" />

                        <field name="bool" invisible="1" />
                        <field name="test" invisible="1"/>
                        <field name="group" invisible="1"/>
                        <field name="proposal_policy" invisible="1"/>

                    </div>
                    <field name="new_proposal_test_ids"  force_save="1" >
                        <tree >
                            <field name="risk"/>
                            <field name="risk_description"/>

                            <button name="get_covers" string="Show Covers" class="oe_highlight" type="object"/>
                            <button name="Show_covers" string="Edit Covers" class="oe_highlight" type="object"/>

                        </tree>
                        <form>

                            <field name="name_cover_risk_ids"    >
                                <tree>
                                    <field name="name"/>
                                    <field name="check"/>
                                    <field name="sum_insure"/>
                                    <field name="rate"/>
                                    <field name="net_perimum"/>
                                </tree>
                                <form>
                                    <group>
                                        <field name="name"   />
                                        <field name="check"/>
                                        <field name="sum_insure"/>
                                        <field name="rate"/>
                                        <field name="net_perimum"/>
                                    </group>
                                </form>

                            </field>
                        </form>
                    </field>
                    <field name="covers_rel_ids"  >
                        <tree>
                            <field name="check" invisible="1"  />
                            <field name="name" attrs="{'readonly': [('check', '=', True)]}"  force_save="1"  />
                            <field name="sum_insure"  attrs="{'readonly': [('check', '=', True)]}" force_save="1"  />
                            <field name="rate" attrs="{'readonly': [('check', '=', True)]}"  force_save="1"  />
                            <field name="net_perimum" attrs="{'readonly': [('check', '=', True)]}" force_save="1"   />

                        </tree>
                        <form>
                            <group>
                                <field name="check" invisible="0" />
                                <field name="name" attrs="{'readonly': [('check', '=', True)]}" force_save="1"  />
                                <field name="sum_insure"  attrs="{'readonly': [('check', '=', True)]}" force_save="1"  />
                                <field name="rate" attrs="{'readonly': [('check', '=', True)]}"  force_save="1"  />
                                <field name="net_perimum"  attrs="{'readonly': [('check', '=', True)]}" force_save="1" />

                            </group>
                        </form>
                    </field>

                    <!--<field name="person_proposal_test"  force_save="1"  attrs="{'invisible': ['|','|',('test', '!=', 'person'),('group', '=', True),('bool','!=',True)]}" >-->

                    <!--<tree>-->
                    <!--<field name="name"  />-->
                    <!--<field name="DOB"  />-->
                    <!--<field name="job"  />-->
                    <!--<field name="covers_person" >-->
                    <!--<tree>-->
                    <!--<field name="name"/>-->
                    <!--<field name="check"/>-->
                    <!--<field name="sum_insure"/>-->
                    <!--<field name="rate"/>-->
                    <!--<field name="net_perimum"/>-->
                    <!--</tree>-->
                    <!--</field>-->
                    <!--<button name="get_covers_person" string="Show Covers" class="oe_highlight" type="object"/>-->
                    <!--<button name="Show_covers_person" string="Edit Covers" class="oe_highlight" type="object"/>-->

                    <!--</tree>-->
                    <!--<form>-->
                    <!--<field name="covers_person"  >-->
                    <!--<tree>-->
                    <!--<field name="name"/>-->
                    <!--<field name="check"/>-->
                    <!--<field name="sum_insure"/>-->
                    <!--<field name="rate"/>-->
                    <!--<field name="net_perimum"/>-->
                    <!--</tree>-->
                    <!--<form>-->
                    <!--<group>-->
                    <!--<field name="name"/>-->
                    <!--<field name="check"/>-->
                    <!--<field name="sum_insure"/>-->
                    <!--<field name="rate"/>-->
                    <!--<field name="net_perimum"/>-->
                    <!--</group>-->
                    <!--</form>-->
                    <!--</field>-->
                    <!--</form>-->
                    <!--</field>-->
                    <!--<field name="cargo_proposal_test"   force_save="1" attrs="{'invisible': ['|','|',('test', '!=', 'cargo'),('group', '=', True),('bool','!=',True)]}" >-->

                    <!--<tree>-->
                    <!--<field name="From"  />-->
                    <!--<field name="To"  />-->
                    <!--<field name="cargo_type"  />-->
                    <!--<field name="weight"  />-->
                    <!--<field name="covers_cargo" >-->
                    <!--<tree>-->
                    <!--<field name="name"/>-->
                    <!--<field name="check"/>-->
                    <!--<field name="sum_insure"/>-->
                    <!--<field name="rate"/>-->
                    <!--<field name="net_perimum"/>-->
                    <!--</tree>-->
                    <!--</field>-->
                    <!--<button name="get_covers_cargo" string="Show Covers" class="oe_highlight" type="object"/>-->
                    <!--<button name="Show_covers_cargo" string="Edit Covers" class="oe_highlight" type="object"/>-->

                    <!--</tree>-->
                    <!--<form>-->
                    <!--<field name="covers_cargo"  >-->
                    <!--<tree>-->
                    <!--<field name="name"/>-->
                    <!--<field name="check"/>-->
                    <!--<field name="sum_insure"/>-->
                    <!--<field name="rate"/>-->
                    <!--<field name="net_perimum"/>-->
                    <!--</tree>-->
                    <!--<form>-->
                    <!--<group>-->
                    <!--<field name="name"/>-->
                    <!--<field name="check"/>-->
                    <!--<field name="sum_insure"/>-->
                    <!--<field name="rate"/>-->
                    <!--<field name="net_perimum"/>-->
                    <!--</group>-->
                    <!--</form>-->
                    <!--</field>-->

                    <!--</form>-->
                    <!--</field>-->
                    <!--<field name="group_proposal"  force_save="1" attrs="{'invisible': [('group', '!=', True)]}" >-->

                    <!--<tree>-->
                    <!--<field name="group_name"   />-->
                    <!--<field name="count"  widget="float" type="char"   />-->
                    <!--<field name="file"    />-->
                    <!--<field name="covers_group" >-->
                    <!--<tree>-->
                    <!--<field name="name"/>-->
                    <!--<field name="check"/>-->
                    <!--<field name="sum_insure"/>-->
                    <!--<field name="rate"/>-->
                    <!--<field name="net_perimum"/>-->
                    <!--</tree>-->
                    <!--</field>-->
                    <!--&lt;!&ndash;<button name="" string="Show Covers" class="oe_highlight" type="object"/>&ndash;&gt;-->

                    <!--</tree>-->
                    <!--<form>-->
                    <!--<field name="covers_group" >-->
                    <!--<tree>-->
                    <!--<field name="name"/>-->
                    <!--<field name="check"/>-->
                    <!--<field name="sum_insure"/>-->
                    <!--<field name="rate"/>-->
                    <!--<field name="net_perimum"/>-->
                    <!--</tree>-->
                    <!--<form>-->
                    <!--<group>-->
                    <!--<field name="name"/>-->
                    <!--<field name="check"/>-->
                    <!--<field name="sum_insure"/>-->
                    <!--<field name="rate"/>-->
                    <!--<field name="net_perimum"/>-->
                    <!--</group>-->

                    <!--</form>-->
                    <!--</field>-->
                    <!--</form>-->
                    <!--</field>-->




                    <!--</field>-->
                </form>
            </field>




        </record>


    </data>
</odoo>